<?xml version="1.0" encoding="UTF-8"?>
<soapenv:Envelope xmlns:soapenv="http://schemas.xmlsoap.org/soap/envelope/">
    <soapenv:Body>
        <soapenv:Fault>
            <faultcode>soapenv:Server</faultcode>
            <faultstring>Policy Falsified</faultstring>
            <faultactor>https://accessgw.tigo.com.gh:8443/live/PurchaseInitiate</faultactor>
            <detail>
                <l7:policyResult status="Assertion Falsified"
                    xmlns:l7="http://www.layer7tech.com/ws/policy/fault" xmlns:l7p="http://www.layer7tech.com/ws/policy">
                    <l7:assertionResult
                        assertion="l7p:RemoteIpAddressRange" status="Assertion Falsified">
                        <l7:detailMessage id="4503">Requestor address 52.214.1.251 is not allowed</l7:detailMessage>
                    </l7:assertionResult>
                    <l7:assertionResult
                        assertion="l7p:RemoteIpAddressRange" status="Assertion Falsified">
                        <l7:detailMessage id="4503">Requestor address 52.214.1.251 is not allowed</l7:detailMessage>
                    </l7:assertionResult>
                    <l7:assertionResult
                        assertion="l7p:RemoteIpAddressRange" status="Assertion Falsified">
                        <l7:detailMessage id="4503">Requestor address 52.214.1.251 is not allowed</l7:detailMessage>
                    </l7:assertionResult>
                    <l7:assertionResult
                        assertion="l7p:RemoteIpAddressRange" status="Assertion Falsified">
                        <l7:detailMessage id="4503">Requestor address 52.214.1.251 is not allowed</l7:detailMessage>
                    </l7:assertionResult>
                    <l7:assertionResult
                        assertion="l7p:RemoteIpAddressRange" status="Assertion Falsified">
                        <l7:detailMessage id="4503">Requestor address 52.214.1.251 is not allowed</l7:detailMessage>
                    </l7:assertionResult>
                    <l7:assertionResult
                        assertion="l7p:RemoteIpAddressRange" status="Assertion Falsified">
                        <l7:detailMessage id="4503">Requestor address 52.214.1.251 is not allowed</l7:detailMessage>
                    </l7:assertionResult>
                    <l7:assertionResult
                        assertion="l7p:RemoteIpAddressRange" status="Assertion Falsified">
                        <l7:detailMessage id="4503">Requestor address 52.214.1.251 is not allowed</l7:detailMessage>
                    </l7:assertionResult>
                    <l7:assertionResult
                        assertion="l7p:RemoteIpAddressRange" status="Assertion Falsified">
                        <l7:detailMessage id="4503">Requestor address 52.214.1.251 is not allowed</l7:detailMessage>
                    </l7:assertionResult>
                    <l7:assertionResult
                        assertion="l7p:RemoteIpAddressRange" status="Assertion Falsified">
                        <l7:detailMessage id="4503">Requestor address 52.214.1.251 is not allowed</l7:detailMessage>
                    </l7:assertionResult>
                    <l7:assertionResult
                        assertion="l7p:RemoteIpAddressRange" status="Assertion Falsified">
                        <l7:detailMessage id="4503">Requestor address 52.214.1.251 is not allowed</l7:detailMessage>
                    </l7:assertionResult>
                    <l7:assertionResult
                        assertion="l7p:RemoteIpAddressRange" status="Assertion Falsified">
                        <l7:detailMessage id="4503">Requestor address 52.214.1.251 is not allowed</l7:detailMessage>
                    </l7:assertionResult>
                    <l7:assertionResult
                        assertion="l7p:RemoteIpAddressRange" status="Assertion Falsified">
                        <l7:detailMessage id="4503">Requestor address 52.214.1.251 is not allowed</l7:detailMessage>
                    </l7:assertionResult>
                    <l7:assertionResult
                        assertion="l7p:RemoteIpAddressRange" status="Assertion Falsified">
                        <l7:detailMessage id="4503">Requestor address 52.214.1.251 is not allowed</l7:detailMessage>
                    </l7:assertionResult>
                    <l7:assertionResult
                        assertion="l7p:RemoteIpAddressRange" status="Assertion Falsified">
                        <l7:detailMessage id="4503">Requestor address 52.214.1.251 is not allowed</l7:detailMessage>
                    </l7:assertionResult>
                    <l7:assertionResult
                        assertion="l7p:RemoteIpAddressRange" status="Assertion Falsified">
                        <l7:detailMessage id="4503">Requestor address 52.214.1.251 is not allowed</l7:detailMessage>
                    </l7:assertionResult>
                    <l7:assertionResult
                        assertion="l7p:RemoteIpAddressRange" status="Assertion Falsified">
                        <l7:detailMessage id="4503">Requestor address 52.214.1.251 is not allowed</l7:detailMessage>
                    </l7:assertionResult>
                    <l7:assertionResult
                        assertion="l7p:RemoteIpAddressRange" status="Assertion Falsified">
                        <l7:detailMessage id="4503">Requestor address 52.214.1.251 is not allowed</l7:detailMessage>
                    </l7:assertionResult>
                    <l7:assertionResult
                        assertion="l7p:RemoteIpAddressRange" status="Assertion Falsified">
                        <l7:detailMessage id="4503">Requestor address 52.214.1.251 is not allowed</l7:detailMessage>
                    </l7:assertionResult>
                    <l7:assertionResult
                        assertion="l7p:RemoteIpAddressRange" status="Assertion Falsified">
                        <l7:detailMessage id="4503">Requestor address 52.214.1.251 is not allowed</l7:detailMessage>
                    </l7:assertionResult>
                    <l7:assertionResult
                        assertion="l7p:RemoteIpAddressRange" status="Assertion Falsified">
                        <l7:detailMessage id="4503">Requestor address 52.214.1.251 is not allowed</l7:detailMessage>
                    </l7:assertionResult>
                    <l7:assertionResult
                        assertion="l7p:RemoteIpAddressRange" status="Assertion Falsified">
                        <l7:detailMessage id="4503">Requestor address 52.214.1.251 is not allowed</l7:detailMessage>
                    </l7:assertionResult>
                    <l7:assertionResult
                        assertion="l7p:RemoteIpAddressRange" status="Assertion Falsified">
                        <l7:detailMessage id="4503">Requestor address 52.214.1.251 is not allowed</l7:detailMessage>
                    </l7:assertionResult>
                    <l7:assertionResult
                        assertion="l7p:RemoteIpAddressRange" status="Assertion Falsified">
                        <l7:detailMessage id="4503">Requestor address 52.214.1.251 is not allowed</l7:detailMessage>
                    </l7:assertionResult>
                    <l7:assertionResult
                        assertion="l7p:RemoteIpAddressRange" status="Assertion Falsified">
                        <l7:detailMessage id="4503">Requestor address 52.214.1.251 is not allowed</l7:detailMessage>
                    </l7:assertionResult>
                    <l7:assertionResult
                        assertion="l7p:RemoteIpAddressRange" status="Assertion Falsified">
                        <l7:detailMessage id="4503">Requestor address 52.214.1.251 is not allowed</l7:detailMessage>
                    </l7:assertionResult>
                    <l7:assertionResult
                        assertion="l7p:RemoteIpAddressRange" status="Assertion Falsified">
                        <l7:detailMessage id="4503">Requestor address 52.214.1.251 is not allowed</l7:detailMessage>
                    </l7:assertionResult>
                    <l7:assertionResult
                        assertion="l7p:RemoteIpAddressRange" status="Assertion Falsified">
                        <l7:detailMessage id="4503">Requestor address 52.214.1.251 is not allowed</l7:detailMessage>
                    </l7:assertionResult>
                    <l7:assertionResult
                        assertion="l7p:RemoteIpAddressRange" status="Assertion Falsified">
                        <l7:detailMessage id="4503">Requestor address 52.214.1.251 is not allowed</l7:detailMessage>
                    </l7:assertionResult>
                    <l7:assertionResult
                        assertion="l7p:RemoteIpAddressRange" status="Assertion Falsified">
                        <l7:detailMessage id="4503">Requestor address 52.214.1.251 is not allowed</l7:detailMessage>
                    </l7:assertionResult>
                    <l7:assertionResult
                        assertion="l7p:RemoteIpAddressRange" status="Assertion Falsified">
                        <l7:detailMessage id="4503">Requestor address 52.214.1.251 is not allowed</l7:detailMessage>
                    </l7:assertionResult>
                    <l7:assertionResult
                        assertion="l7p:RemoteIpAddressRange" status="Assertion Falsified">
                        <l7:detailMessage id="4503">Requestor address 52.214.1.251 is not allowed</l7:detailMessage>
                    </l7:assertionResult>
                    <l7:assertionResult
                        assertion="l7p:RemoteIpAddressRange" status="Assertion Falsified">
                        <l7:detailMessage id="4503">Requestor address 52.214.1.251 is not allowed</l7:detailMessage>
                    </l7:assertionResult>
                    <l7:assertionResult
                        assertion="l7p:RemoteIpAddressRange" status="Assertion Falsified">
                        <l7:detailMessage id="4503">Requestor address 52.214.1.251 is not allowed</l7:detailMessage>
                    </l7:assertionResult>
                    <l7:assertionResult
                        assertion="l7p:RemoteIpAddressRange" status="Assertion Falsified">
                        <l7:detailMessage id="4503">Requestor address 52.214.1.251 is not allowed</l7:detailMessage>
                    </l7:assertionResult>
                    <l7:assertionResult
                        assertion="l7p:RemoteIpAddressRange" status="Assertion Falsified">
                        <l7:detailMessage id="4503">Requestor address 52.214.1.251 is not allowed</l7:detailMessage>
                    </l7:assertionResult>
                    <l7:assertionResult
                        assertion="l7p:RemoteIpAddressRange" status="Assertion Falsified">
                        <l7:detailMessage id="4503">Requestor address 52.214.1.251 is not allowed</l7:detailMessage>
                    </l7:assertionResult>
                    <l7:assertionResult
                        assertion="l7p:RemoteIpAddressRange" status="Assertion Falsified">
                        <l7:detailMessage id="4503">Requestor address 52.214.1.251 is not allowed</l7:detailMessage>
                    </l7:assertionResult>
                    <l7:assertionResult
                        assertion="l7p:RemoteIpAddressRange" status="Assertion Falsified">
                        <l7:detailMessage id="4503">Requestor address 52.214.1.251 is not allowed</l7:detailMessage>
                    </l7:assertionResult>
                    <l7:assertionResult
                        assertion="l7p:RemoteIpAddressRange" status="Assertion Falsified">
                        <l7:detailMessage id="4503">Requestor address 52.214.1.251 is not allowed</l7:detailMessage>
                    </l7:assertionResult>
                    <l7:assertionResult
                        assertion="l7p:RemoteIpAddressRange" status="Assertion Falsified">
                        <l7:detailMessage id="4503">Requestor address 52.214.1.251 is not allowed</l7:detailMessage>
                    </l7:assertionResult>
                    <l7:assertionResult
                        assertion="l7p:RemoteIpAddressRange" status="Assertion Falsified">
                        <l7:detailMessage id="4503">Requestor address 52.214.1.251 is not allowed</l7:detailMessage>
                    </l7:assertionResult>
                    <l7:assertionResult
                        assertion="l7p:RemoteIpAddressRange" status="Assertion Falsified">
                        <l7:detailMessage id="4503">Requestor address 52.214.1.251 is not allowed</l7:detailMessage>
                    </l7:assertionResult>
                    <l7:assertionResult
                        assertion="l7p:RemoteIpAddressRange" status="Assertion Falsified">
                        <l7:detailMessage id="4503">Requestor address 52.214.1.251 is not allowed</l7:detailMessage>
                    </l7:assertionResult>
                    <l7:assertionResult
                        assertion="l7p:RemoteIpAddressRange" status="Assertion Falsified">
                        <l7:detailMessage id="4503">Requestor address 52.214.1.251 is not allowed</l7:detailMessage>
                    </l7:assertionResult>
                    <l7:assertionResult
                        assertion="l7p:RemoteIpAddressRange" status="Assertion Falsified">
                        <l7:detailMessage id="4503">Requestor address 52.214.1.251 is not allowed</l7:detailMessage>
                    </l7:assertionResult>
                    <l7:assertionResult
                        assertion="l7p:RemoteIpAddressRange" status="Assertion Falsified">
                        <l7:detailMessage id="4503">Requestor address 52.214.1.251 is not allowed</l7:detailMessage>
                    </l7:assertionResult>
                    <l7:assertionResult
                        assertion="l7p:RemoteIpAddressRange" status="Assertion Falsified">
                        <l7:detailMessage id="4503">Requestor address 52.214.1.251 is not allowed</l7:detailMessage>
                    </l7:assertionResult>
                    <l7:assertionResult
                        assertion="l7p:RemoteIpAddressRange" status="Assertion Falsified">
                        <l7:detailMessage id="4503">Requestor address 52.214.1.251 is not allowed</l7:detailMessage>
                    </l7:assertionResult>
                    <l7:assertionResult
                        assertion="l7p:RemoteIpAddressRange" status="Assertion Falsified">
                        <l7:detailMessage id="4503">Requestor address 52.214.1.251 is not allowed</l7:detailMessage>
                    </l7:assertionResult>
                    <l7:assertionResult
                        assertion="l7p:RemoteIpAddressRange" status="Assertion Falsified">
                        <l7:detailMessage id="4503">Requestor address 52.214.1.251 is not allowed</l7:detailMessage>
                    </l7:assertionResult>
                    <l7:assertionResult
                        assertion="l7p:RemoteIpAddressRange" status="Assertion Falsified">
                        <l7:detailMessage id="4503">Requestor address 52.214.1.251 is not allowed</l7:detailMessage>
                    </l7:assertionResult>
                    <l7:assertionResult
                        assertion="l7p:RemoteIpAddressRange" status="Assertion Falsified">
                        <l7:detailMessage id="4503">Requestor address 52.214.1.251 is not allowed</l7:detailMessage>
                    </l7:assertionResult>
                    <l7:assertionResult
                        assertion="l7p:RemoteIpAddressRange" status="Assertion Falsified">
                        <l7:detailMessage id="4503">Requestor address 52.214.1.251 is not allowed</l7:detailMessage>
                    </l7:assertionResult>
                    <l7:assertionResult
                        assertion="l7p:RemoteIpAddressRange" status="Assertion Falsified">
                        <l7:detailMessage id="4503">Requestor address 52.214.1.251 is not allowed</l7:detailMessage>
                    </l7:assertionResult>
                    <l7:assertionResult
                        assertion="l7p:RemoteIpAddressRange" status="Assertion Falsified">
                        <l7:detailMessage id="4503">Requestor address 52.214.1.251 is not allowed</l7:detailMessage>
                    </l7:assertionResult>
                    <l7:assertionResult
                        assertion="l7p:RemoteIpAddressRange" status="Assertion Falsified">
                        <l7:detailMessage id="4503">Requestor address 52.214.1.251 is not allowed</l7:detailMessage>
                    </l7:assertionResult>
                    <l7:assertionResult
                        assertion="l7p:RemoteIpAddressRange" status="Assertion Falsified">
                        <l7:detailMessage id="4503">Requestor address 52.214.1.251 is not allowed</l7:detailMessage>
                    </l7:assertionResult>
                    <l7:assertionResult
                        assertion="l7p:RemoteIpAddressRange" status="Assertion Falsified">
                        <l7:detailMessage id="4503">Requestor address 52.214.1.251 is not allowed</l7:detailMessage>
                    </l7:assertionResult>
                    <l7:assertionResult
                        assertion="l7p:RemoteIpAddressRange" status="Assertion Falsified">
                        <l7:detailMessage id="4503">Requestor address 52.214.1.251 is not allowed</l7:detailMessage>
                    </l7:assertionResult>
                    <l7:assertionResult
                        assertion="l7p:RemoteIpAddressRange" status="Assertion Falsified">
                        <l7:detailMessage id="4503">Requestor address 52.214.1.251 is not allowed</l7:detailMessage>
                    </l7:assertionResult>
                    <l7:assertionResult
                        assertion="l7p:RemoteIpAddressRange" status="Assertion Falsified">
                        <l7:detailMessage id="4503">Requestor address 52.214.1.251 is not allowed</l7:detailMessage>
                    </l7:assertionResult>
                    <l7:assertionResult
                        assertion="l7p:RemoteIpAddressRange" status="Assertion Falsified">
                        <l7:detailMessage id="4503">Requestor address 52.214.1.251 is not allowed</l7:detailMessage>
                    </l7:assertionResult>
                    <l7:assertionResult
                        assertion="l7p:RemoteIpAddressRange" status="Assertion Falsified">
                        <l7:detailMessage id="4503">Requestor address 52.214.1.251 is not allowed</l7:detailMessage>
                    </l7:assertionResult>
                    <l7:assertionResult
                        assertion="l7p:RemoteIpAddressRange" status="Assertion Falsified">
                        <l7:detailMessage id="4503">Requestor address 52.214.1.251 is not allowed</l7:detailMessage>
                    </l7:assertionResult>
                    <l7:assertionResult
                        assertion="l7p:RemoteIpAddressRange" status="Assertion Falsified">
                        <l7:detailMessage id="4503">Requestor address 52.214.1.251 is not allowed</l7:detailMessage>
                    </l7:assertionResult>
                    <l7:assertionResult
                        assertion="l7p:RemoteIpAddressRange" status="Assertion Falsified">
                        <l7:detailMessage id="4503">Requestor address 52.214.1.251 is not allowed</l7:detailMessage>
                    </l7:assertionResult>
                    <l7:assertionResult
                        assertion="l7p:RemoteIpAddressRange" status="Assertion Falsified">
                        <l7:detailMessage id="4503">Requestor address 52.214.1.251 is not allowed</l7:detailMessage>
                    </l7:assertionResult>
                    <l7:assertionResult
                        assertion="l7p:RemoteIpAddressRange" status="Assertion Falsified">
                        <l7:detailMessage id="4503">Requestor address 52.214.1.251 is not allowed</l7:detailMessage>
                    </l7:assertionResult>
                    <l7:assertionResult
                        assertion="l7p:RemoteIpAddressRange" status="Assertion Falsified">
                        <l7:detailMessage id="4503">Requestor address 52.214.1.251 is not allowed</l7:detailMessage>
                    </l7:assertionResult>
                    <l7:assertionResult
                        assertion="l7p:RemoteIpAddressRange" status="Assertion Falsified">
                        <l7:detailMessage id="4503">Requestor address 52.214.1.251 is not allowed</l7:detailMessage>
                    </l7:assertionResult>
                    <l7:assertionResult
                        assertion="l7p:RemoteIpAddressRange" status="Assertion Falsified">
                        <l7:detailMessage id="4503">Requestor address 52.214.1.251 is not allowed</l7:detailMessage>
                    </l7:assertionResult>
                    <l7:assertionResult
                        assertion="l7p:RemoteIpAddressRange" status="Assertion Falsified">
                        <l7:detailMessage id="4503">Requestor address 52.214.1.251 is not allowed</l7:detailMessage>
                    </l7:assertionResult>
                    <l7:assertionResult
                        assertion="l7p:RemoteIpAddressRange" status="Assertion Falsified">
                        <l7:detailMessage id="4503">Requestor address 52.214.1.251 is not allowed</l7:detailMessage>
                    </l7:assertionResult>
                    <l7:assertionResult
                        assertion="l7p:RemoteIpAddressRange" status="Assertion Falsified">
                        <l7:detailMessage id="4503">Requestor address 52.214.1.251 is not allowed</l7:detailMessage>
                    </l7:assertionResult>
                    <l7:assertionResult
                        assertion="l7p:RemoteIpAddressRange" status="Assertion Falsified">
                        <l7:detailMessage id="4503">Requestor address 52.214.1.251 is not allowed</l7:detailMessage>
                    </l7:assertionResult>
                    <l7:assertionResult
                        assertion="l7p:RemoteIpAddressRange" status="Assertion Falsified">
                        <l7:detailMessage id="4503">Requestor address 52.214.1.251 is not allowed</l7:detailMessage>
                    </l7:assertionResult>
                    <l7:assertionResult
                        assertion="l7p:RemoteIpAddressRange" status="Assertion Falsified">
                        <l7:detailMessage id="4503">Requestor address 52.214.1.251 is not allowed</l7:detailMessage>
                    </l7:assertionResult>
                    <l7:assertionResult
                        assertion="l7p:RemoteIpAddressRange" status="Assertion Falsified">
                        <l7:detailMessage id="4503">Requestor address 52.214.1.251 is not allowed</l7:detailMessage>
                    </l7:assertionResult>
                    <l7:assertionResult
                        assertion="l7p:RemoteIpAddressRange" status="Assertion Falsified">
                        <l7:detailMessage id="4503">Requestor address 52.214.1.251 is not allowed</l7:detailMessage>
                    </l7:assertionResult>
                    <l7:assertionResult
                        assertion="l7p:RemoteIpAddressRange" status="Assertion Falsified">
                        <l7:detailMessage id="4503">Requestor address 52.214.1.251 is not allowed</l7:detailMessage>
                    </l7:assertionResult>
                    <l7:assertionResult
                        assertion="l7p:RemoteIpAddressRange" status="Assertion Falsified">
                        <l7:detailMessage id="4503">Requestor address 52.214.1.251 is not allowed</l7:detailMessage>
                    </l7:assertionResult>
                    <l7:assertionResult
                        assertion="l7p:RemoteIpAddressRange" status="Assertion Falsified">
                        <l7:detailMessage id="4503">Requestor address 52.214.1.251 is not allowed</l7:detailMessage>
                    </l7:assertionResult>
                    <l7:assertionResult
                        assertion="l7p:RemoteIpAddressRange" status="Assertion Falsified">
                        <l7:detailMessage id="4503">Requestor address 52.214.1.251 is not allowed</l7:detailMessage>
                    </l7:assertionResult>
                    <l7:assertionResult
                        assertion="l7p:RemoteIpAddressRange" status="Assertion Falsified">
                        <l7:detailMessage id="4503">Requestor address 52.214.1.251 is not allowed</l7:detailMessage>
                    </l7:assertionResult>
                    <l7:assertionResult
                        assertion="l7p:RemoteIpAddressRange" status="Assertion Falsified">
                        <l7:detailMessage id="4503">Requestor address 52.214.1.251 is not allowed</l7:detailMessage>
                    </l7:assertionResult>
                    <l7:assertionResult
                        assertion="l7p:RemoteIpAddressRange" status="Assertion Falsified">
                        <l7:detailMessage id="4503">Requestor address 52.214.1.251 is not allowed</l7:detailMessage>
                    </l7:assertionResult>
                    <l7:assertionResult
                        assertion="l7p:RemoteIpAddressRange" status="Assertion Falsified">
                        <l7:detailMessage id="4503">Requestor address 52.214.1.251 is not allowed</l7:detailMessage>
                    </l7:assertionResult>
                    <l7:assertionResult
                        assertion="l7p:RemoteIpAddressRange" status="Assertion Falsified">
                        <l7:detailMessage id="4503">Requestor address 52.214.1.251 is not allowed</l7:detailMessage>
                    </l7:assertionResult>
                    <l7:assertionResult
                        assertion="l7p:RemoteIpAddressRange" status="Assertion Falsified">
                        <l7:detailMessage id="4503">Requestor address 52.214.1.251 is not allowed</l7:detailMessage>
                    </l7:assertionResult>
                    <l7:assertionResult
                        assertion="l7p:RemoteIpAddressRange" status="Assertion Falsified">
                        <l7:detailMessage id="4503">Requestor address 52.214.1.251 is not allowed</l7:detailMessage>
                    </l7:assertionResult>
                    <l7:assertionResult
                        assertion="l7p:RemoteIpAddressRange" status="Assertion Falsified">
                        <l7:detailMessage id="4503">Requestor address 52.214.1.251 is not allowed</l7:detailMessage>
                    </l7:assertionResult>
                    <l7:assertionResult
                        assertion="l7p:RemoteIpAddressRange" status="Assertion Falsified">
                        <l7:detailMessage id="4503">Requestor address 52.214.1.251 is not allowed</l7:detailMessage>
                    </l7:assertionResult>
                    <l7:assertionResult
                        assertion="l7p:RemoteIpAddressRange" status="Assertion Falsified">
                        <l7:detailMessage id="4503">Requestor address 52.214.1.251 is not allowed</l7:detailMessage>
                    </l7:assertionResult>
                    <l7:assertionResult
                        assertion="l7p:RemoteIpAddressRange" status="Assertion Falsified">
                        <l7:detailMessage id="4503">Requestor address 52.214.1.251 is not allowed</l7:detailMessage>
                    </l7:assertionResult>
                    <l7:assertionResult
                        assertion="l7p:RemoteIpAddressRange" status="Assertion Falsified">
                        <l7:detailMessage id="4503">Requestor address 52.214.1.251 is not allowed</l7:detailMessage>
                    </l7:assertionResult>
                    <l7:assertionResult
                        assertion="l7p:RemoteIpAddressRange" status="Assertion Falsified">
                        <l7:detailMessage id="4503">Requestor address 52.214.1.251 is not allowed</l7:detailMessage>
                    </l7:assertionResult>
                    <l7:assertionResult
                        assertion="l7p:RemoteIpAddressRange" status="Assertion Falsified">
                        <l7:detailMessage id="4503">Requestor address 52.214.1.251 is not allowed</l7:detailMessage>
                    </l7:assertionResult>
                    <l7:assertionResult
                        assertion="l7p:RemoteIpAddressRange" status="Assertion Falsified">
                        <l7:detailMessage id="4503">Requestor address 52.214.1.251 is not allowed</l7:detailMessage>
                    </l7:assertionResult>
                    <l7:assertionResult
                        assertion="l7p:RemoteIpAddressRange" status="Assertion Falsified">
                        <l7:detailMessage id="4503">Requestor address 52.214.1.251 is not allowed</l7:detailMessage>
                    </l7:assertionResult>
                    <l7:assertionResult
                        assertion="l7p:RemoteIpAddressRange" status="Assertion Falsified">
                        <l7:detailMessage id="4503">Requestor address 52.214.1.251 is not allowed</l7:detailMessage>
                    </l7:assertionResult>
                    <l7:assertionResult
                        assertion="l7p:RemoteIpAddressRange" status="Assertion Falsified">
                        <l7:detailMessage id="4503">Requestor address 52.214.1.251 is not allowed</l7:detailMessage>
                    </l7:assertionResult>
                    <l7:assertionResult
                        assertion="l7p:RemoteIpAddressRange" status="Assertion Falsified">
                        <l7:detailMessage id="4503">Requestor address 52.214.1.251 is not allowed</l7:detailMessage>
                    </l7:assertionResult>
                    <l7:assertionResult
                        assertion="l7p:RemoteIpAddressRange" status="Assertion Falsified">
                        <l7:detailMessage id="4503">Requestor address 52.214.1.251 is not allowed</l7:detailMessage>
                    </l7:assertionResult>
                    <l7:assertionResult
                        assertion="l7p:RemoteIpAddressRange" status="Assertion Falsified">
                        <l7:detailMessage id="4503">Requestor address 52.214.1.251 is not allowed</l7:detailMessage>
                    </l7:assertionResult>
                    <l7:assertionResult
                        assertion="l7p:RemoteIpAddressRange" status="Assertion Falsified">
                        <l7:detailMessage id="4503">Requestor address 52.214.1.251 is not allowed</l7:detailMessage>
                    </l7:assertionResult>
                    <l7:assertionResult
                        assertion="l7p:RemoteIpAddressRange" status="Assertion Falsified">
                        <l7:detailMessage id="4503">Requestor address 52.214.1.251 is not allowed</l7:detailMessage>
                    </l7:assertionResult>
                    <l7:assertionResult
                        assertion="l7p:RemoteIpAddressRange" status="Assertion Falsified">
                        <l7:detailMessage id="4503">Requestor address 52.214.1.251 is not allowed</l7:detailMessage>
                    </l7:assertionResult>
                    <l7:assertionResult
                        assertion="l7p:RemoteIpAddressRange" status="Assertion Falsified">
                        <l7:detailMessage id="4503">Requestor address 52.214.1.251 is not allowed</l7:detailMessage>
                    </l7:assertionResult>
                    <l7:assertionResult
                        assertion="l7p:RemoteIpAddressRange" status="Assertion Falsified">
                        <l7:detailMessage id="4503">Requestor address 52.214.1.251 is not allowed</l7:detailMessage>
                    </l7:assertionResult>
                    <l7:assertionResult
                        assertion="l7p:RemoteIpAddressRange" status="Assertion Falsified">
                        <l7:detailMessage id="4503">Requestor address 52.214.1.251 is not allowed</l7:detailMessage>
                    </l7:assertionResult>
                    <l7:assertionResult
                        assertion="l7p:RemoteIpAddressRange" status="Assertion Falsified">
                        <l7:detailMessage id="4503">Requestor address 52.214.1.251 is not allowed</l7:detailMessage>
                    </l7:assertionResult>
                    <l7:assertionResult
                        assertion="l7p:RemoteIpAddressRange" status="Assertion Falsified">
                        <l7:detailMessage id="4503">Requestor address 52.214.1.251 is not allowed</l7:detailMessage>
                    </l7:assertionResult>
                    <l7:assertionResult
                        assertion="l7p:RemoteIpAddressRange" status="Assertion Falsified">
                        <l7:detailMessage id="4503">Requestor address 52.214.1.251 is not allowed</l7:detailMessage>
                    </l7:assertionResult>
                    <l7:assertionResult
                        assertion="l7p:RemoteIpAddressRange" status="Assertion Falsified">
                        <l7:detailMessage id="4503">Requestor address 52.214.1.251 is not allowed</l7:detailMessage>
                    </l7:assertionResult>
                    <l7:assertionResult
                        assertion="l7p:RemoteIpAddressRange" status="Assertion Falsified">
                        <l7:detailMessage id="4503">Requestor address 52.214.1.251 is not allowed</l7:detailMessage>
                    </l7:assertionResult>
                    <l7:assertionResult
                        assertion="l7p:RemoteIpAddressRange" status="Assertion Falsified">
                        <l7:detailMessage id="4503">Requestor address 52.214.1.251 is not allowed</l7:detailMessage>
                    </l7:assertionResult>
                    <l7:assertionResult
                        assertion="l7p:RemoteIpAddressRange" status="Assertion Falsified">
                        <l7:detailMessage id="4503">Requestor address 52.214.1.251 is not allowed</l7:detailMessage>
                    </l7:assertionResult>
                    <l7:assertionResult
                        assertion="l7p:RemoteIpAddressRange" status="Assertion Falsified">
                        <l7:detailMessage id="4503">Requestor address 52.214.1.251 is not allowed</l7:detailMessage>
                    </l7:assertionResult>
                    <l7:assertionResult
                        assertion="l7p:RemoteIpAddressRange" status="Assertion Falsified">
                        <l7:detailMessage id="4503">Requestor address 52.214.1.251 is not allowed</l7:detailMessage>
                    </l7:assertionResult>
                    <l7:assertionResult
                        assertion="l7p:RemoteIpAddressRange" status="Assertion Falsified">
                        <l7:detailMessage id="4503">Requestor address 52.214.1.251 is not allowed</l7:detailMessage>
                    </l7:assertionResult>
                    <l7:assertionResult
                        assertion="l7p:RemoteIpAddressRange" status="Assertion Falsified">
                        <l7:detailMessage id="4503">Requestor address 52.214.1.251 is not allowed</l7:detailMessage>
                    </l7:assertionResult>
                    <l7:assertionResult
                        assertion="l7p:RemoteIpAddressRange" status="Assertion Falsified">
                        <l7:detailMessage id="4503">Requestor address 52.214.1.251 is not allowed</l7:detailMessage>
                    </l7:assertionResult>
                    <l7:assertionResult
                        assertion="l7p:RemoteIpAddressRange" status="Assertion Falsified">
                        <l7:detailMessage id="4503">Requestor address 52.214.1.251 is not allowed</l7:detailMessage>
                    </l7:assertionResult>
                    <l7:assertionResult
                        assertion="l7p:RemoteIpAddressRange" status="Assertion Falsified">
                        <l7:detailMessage id="4503">Requestor address 52.214.1.251 is not allowed</l7:detailMessage>
                    </l7:assertionResult>
                    <l7:assertionResult
                        assertion="l7p:RemoteIpAddressRange" status="Assertion Falsified">
                        <l7:detailMessage id="4503">Requestor address 52.214.1.251 is not allowed</l7:detailMessage>
                    </l7:assertionResult>
                    <l7:assertionResult
                        assertion="l7p:RemoteIpAddressRange" status="Assertion Falsified">
                        <l7:detailMessage id="4503">Requestor address 52.214.1.251 is not allowed</l7:detailMessage>
                    </l7:assertionResult>
                    <l7:assertionResult
                        assertion="l7p:RemoteIpAddressRange" status="Assertion Falsified">
                        <l7:detailMessage id="4503">Requestor address 52.214.1.251 is not allowed</l7:detailMessage>
                    </l7:assertionResult>
                    <l7:assertionResult
                        assertion="l7p:RemoteIpAddressRange" status="Assertion Falsified">
                        <l7:detailMessage id="4503">Requestor address 52.214.1.251 is not allowed</l7:detailMessage>
                    </l7:assertionResult>
                    <l7:assertionResult
                        assertion="l7p:RemoteIpAddressRange" status="Assertion Falsified">
                        <l7:detailMessage id="4503">Requestor address 52.214.1.251 is not allowed</l7:detailMessage>
                    </l7:assertionResult>
                    <l7:assertionResult
                        assertion="l7p:RemoteIpAddressRange" status="Assertion Falsified">
                        <l7:detailMessage id="4503">Requestor address 52.214.1.251 is not allowed</l7:detailMessage>
                    </l7:assertionResult>
                    <l7:assertionResult
                        assertion="l7p:RemoteIpAddressRange" status="Assertion Falsified">
                        <l7:detailMessage id="4503">Requestor address 52.214.1.251 is not allowed</l7:detailMessage>
                    </l7:assertionResult>
                    <l7:assertionResult
                        assertion="l7p:RemoteIpAddressRange" status="Assertion Falsified">
                        <l7:detailMessage id="4503">Requestor address 52.214.1.251 is not allowed</l7:detailMessage>
                    </l7:assertionResult>
                    <l7:assertionResult
                        assertion="l7p:RemoteIpAddressRange" status="Assertion Falsified">
                        <l7:detailMessage id="4503">Requestor address 52.214.1.251 is not allowed</l7:detailMessage>
                    </l7:assertionResult>
                    <l7:assertionResult
                        assertion="l7p:RemoteIpAddressRange" status="Assertion Falsified">
                        <l7:detailMessage id="4503">Requestor address 52.214.1.251 is not allowed</l7:detailMessage>
                    </l7:assertionResult>
                    <l7:assertionResult
                        assertion="l7p:RemoteIpAddressRange" status="Assertion Falsified">
                        <l7:detailMessage id="4503">Requestor address 52.214.1.251 is not allowed</l7:detailMessage>
                    </l7:assertionResult>
                    <l7:assertionResult
                        assertion="l7p:RemoteIpAddressRange" status="Assertion Falsified">
                        <l7:detailMessage id="4503">Requestor address 52.214.1.251 is not allowed</l7:detailMessage>
                    </l7:assertionResult>
                    <l7:assertionResult
                        assertion="l7p:RemoteIpAddressRange" status="Assertion Falsified">
                        <l7:detailMessage id="4503">Requestor address 52.214.1.251 is not allowed</l7:detailMessage>
                    </l7:assertionResult>
                    <l7:assertionResult
                        assertion="l7p:RemoteIpAddressRange" status="Assertion Falsified">
                        <l7:detailMessage id="4503">Requestor address 52.214.1.251 is not allowed</l7:detailMessage>
                    </l7:assertionResult>
                    <l7:assertionResult
                        assertion="l7p:RemoteIpAddressRange" status="Assertion Falsified">
                        <l7:detailMessage id="4503">Requestor address 52.214.1.251 is not allowed</l7:detailMessage>
                    </l7:assertionResult>
                    <l7:assertionResult
                        assertion="l7p:RemoteIpAddressRange" status="Assertion Falsified">
                        <l7:detailMessage id="4503">Requestor address 52.214.1.251 is not allowed</l7:detailMessage>
                    </l7:assertionResult>
                    <l7:assertionResult
                        assertion="l7p:RemoteIpAddressRange" status="Assertion Falsified">
                        <l7:detailMessage id="4503">Requestor address 52.214.1.251 is not allowed</l7:detailMessage>
                    </l7:assertionResult>
                    <l7:assertionResult
                        assertion="l7p:RemoteIpAddressRange" status="Assertion Falsified">
                        <l7:detailMessage id="4503">Requestor address 52.214.1.251 is not allowed</l7:detailMessage>
                    </l7:assertionResult>
                    <l7:assertionResult
                        assertion="l7p:RemoteIpAddressRange" status="Assertion Falsified">
                        <l7:detailMessage id="4503">Requestor address 52.214.1.251 is not allowed</l7:detailMessage>
                    </l7:assertionResult>
                    <l7:assertionResult
                        assertion="l7p:RemoteIpAddressRange" status="Assertion Falsified">
                        <l7:detailMessage id="4503">Requestor address 52.214.1.251 is not allowed</l7:detailMessage>
                    </l7:assertionResult>
                    <l7:assertionResult
                        assertion="l7p:RemoteIpAddressRange" status="Assertion Falsified">
                        <l7:detailMessage id="4503">Requestor address 52.214.1.251 is not allowed</l7:detailMessage>
                    </l7:assertionResult>
                    <l7:assertionResult
                        assertion="l7p:RemoteIpAddressRange" status="Assertion Falsified">
                        <l7:detailMessage id="4503">Requestor address 52.214.1.251 is not allowed</l7:detailMessage>
                    </l7:assertionResult>
                    <l7:assertionResult
                        assertion="l7p:RemoteIpAddressRange" status="Assertion Falsified">
                        <l7:detailMessage id="4503">Requestor address 52.214.1.251 is not allowed</l7:detailMessage>
                    </l7:assertionResult>
                    <l7:assertionResult
                        assertion="l7p:RemoteIpAddressRange" status="Assertion Falsified">
                        <l7:detailMessage id="4503">Requestor address 52.214.1.251 is not allowed</l7:detailMessage>
                    </l7:assertionResult>
                    <l7:assertionResult
                        assertion="l7p:RemoteIpAddressRange" status="Assertion Falsified">
                        <l7:detailMessage id="4503">Requestor address 52.214.1.251 is not allowed</l7:detailMessage>
                    </l7:assertionResult>
                    <l7:assertionResult
                        assertion="l7p:RemoteIpAddressRange" status="Assertion Falsified">
                        <l7:detailMessage id="4503">Requestor address 52.214.1.251 is not allowed</l7:detailMessage>
                    </l7:assertionResult>
                    <l7:assertionResult
                        assertion="l7p:RemoteIpAddressRange" status="Assertion Falsified">
                        <l7:detailMessage id="4503">Requestor address 52.214.1.251 is not allowed</l7:detailMessage>
                    </l7:assertionResult>
                    <l7:assertionResult
                        assertion="l7p:RemoteIpAddressRange" status="Assertion Falsified">
                        <l7:detailMessage id="4503">Requestor address 52.214.1.251 is not allowed</l7:detailMessage>
                    </l7:assertionResult>
                    <l7:assertionResult
                        assertion="l7p:RemoteIpAddressRange" status="Assertion Falsified">
                        <l7:detailMessage id="4503">Requestor address 52.214.1.251 is not allowed</l7:detailMessage>
                    </l7:assertionResult>
                    <l7:assertionResult
                        assertion="l7p:RemoteIpAddressRange" status="Assertion Falsified">
                        <l7:detailMessage id="4503">Requestor address 52.214.1.251 is not allowed</l7:detailMessage>
                    </l7:assertionResult>
                    <l7:assertionResult
                        assertion="l7p:RemoteIpAddressRange" status="Assertion Falsified">
                        <l7:detailMessage id="4503">Requestor address 52.214.1.251 is not allowed</l7:detailMessage>
                    </l7:assertionResult>
                    <l7:assertionResult
                        assertion="l7p:RemoteIpAddressRange" status="Assertion Falsified">
                        <l7:detailMessage id="4503">Requestor address 52.214.1.251 is not allowed</l7:detailMessage>
                    </l7:assertionResult>
                    <l7:assertionResult
                        assertion="l7p:RemoteIpAddressRange" status="Assertion Falsified">
                        <l7:detailMessage id="4503">Requestor address 52.214.1.251 is not allowed</l7:detailMessage>
                    </l7:assertionResult>
                    <l7:assertionResult
                        assertion="l7p:RemoteIpAddressRange" status="Assertion Falsified">
                        <l7:detailMessage id="4503">Requestor address 52.214.1.251 is not allowed</l7:detailMessage>
                    </l7:assertionResult>
                    <l7:assertionResult
                        assertion="l7p:RemoteIpAddressRange" status="Assertion Falsified">
                        <l7:detailMessage id="4503">Requestor address 52.214.1.251 is not allowed</l7:detailMessage>
                    </l7:assertionResult>
                    <l7:assertionResult
                        assertion="l7p:RemoteIpAddressRange" status="Assertion Falsified">
                        <l7:detailMessage id="4503">Requestor address 52.214.1.251 is not allowed</l7:detailMessage>
                    </l7:assertionResult>
                    <l7:assertionResult
                        assertion="l7p:RemoteIpAddressRange" status="Assertion Falsified">
                        <l7:detailMessage id="4503">Requestor address 52.214.1.251 is not allowed</l7:detailMessage>
                    </l7:assertionResult>
                    <l7:assertionResult
                        assertion="l7p:RemoteIpAddressRange" status="Assertion Falsified">
                        <l7:detailMessage id="4503">Requestor address 52.214.1.251 is not allowed</l7:detailMessage>
                    </l7:assertionResult>
                    <l7:assertionResult
                        assertion="l7p:RemoteIpAddressRange" status="Assertion Falsified">
                        <l7:detailMessage id="4503">Requestor address 52.214.1.251 is not allowed</l7:detailMessage>
                    </l7:assertionResult>
                    <l7:assertionResult
                        assertion="l7p:RemoteIpAddressRange" status="Assertion Falsified">
                        <l7:detailMessage id="4503">Requestor address 52.214.1.251 is not allowed</l7:detailMessage>
                    </l7:assertionResult>
                    <l7:assertionResult
                        assertion="l7p:RemoteIpAddressRange" status="Assertion Falsified">
                        <l7:detailMessage id="4503">Requestor address 52.214.1.251 is not allowed</l7:detailMessage>
                    </l7:assertionResult>
                    <l7:assertionResult
                        assertion="l7p:RemoteIpAddressRange" status="Assertion Falsified">
                        <l7:detailMessage id="4503">Requestor address 52.214.1.251 is not allowed</l7:detailMessage>
                    </l7:assertionResult>
                    <l7:assertionResult
                        assertion="l7p:RemoteIpAddressRange" status="Assertion Falsified">
                        <l7:detailMessage id="4503">Requestor address 52.214.1.251 is not allowed</l7:detailMessage>
                    </l7:assertionResult>
                    <l7:assertionResult
                        assertion="l7p:RemoteIpAddressRange" status="Assertion Falsified">
                        <l7:detailMessage id="4503">Requestor address 52.214.1.251 is not allowed</l7:detailMessage>
                    </l7:assertionResult>
                    <l7:assertionResult
                        assertion="l7p:RemoteIpAddressRange" status="Assertion Falsified">
                        <l7:detailMessage id="4503">Requestor address 52.214.1.251 is not allowed</l7:detailMessage>
                    </l7:assertionResult>
                    <l7:assertionResult
                        assertion="l7p:RemoteIpAddressRange" status="Assertion Falsified">
                        <l7:detailMessage id="4503">Requestor address 52.214.1.251 is not allowed</l7:detailMessage>
                    </l7:assertionResult>
                    <l7:assertionResult
                        assertion="l7p:RemoteIpAddressRange" status="Assertion Falsified">
                        <l7:detailMessage id="4503">Requestor address 52.214.1.251 is not allowed</l7:detailMessage>
                    </l7:assertionResult>
                    <l7:assertionResult
                        assertion="l7p:RemoteIpAddressRange" status="Assertion Falsified">
                        <l7:detailMessage id="4503">Requestor address 52.214.1.251 is not allowed</l7:detailMessage>
                    </l7:assertionResult>
                    <l7:assertionResult
                        assertion="l7p:RemoteIpAddressRange" status="Assertion Falsified">
                        <l7:detailMessage id="4503">Requestor address 52.214.1.251 is not allowed</l7:detailMessage>
                    </l7:assertionResult>
                    <l7:assertionResult
                        assertion="l7p:RemoteIpAddressRange" status="Assertion Falsified">
                        <l7:detailMessage id="4503">Requestor address 52.214.1.251 is not allowed</l7:detailMessage>
                    </l7:assertionResult>
                    <l7:assertionResult
                        assertion="l7p:RemoteIpAddressRange" status="Assertion Falsified">
                        <l7:detailMessage id="4503">Requestor address 52.214.1.251 is not allowed</l7:detailMessage>
                    </l7:assertionResult>
                    <l7:assertionResult
                        assertion="l7p:RemoteIpAddressRange" status="Assertion Falsified">
                        <l7:detailMessage id="4503">Requestor address 52.214.1.251 is not allowed</l7:detailMessage>
                    </l7:assertionResult>
                    <l7:assertionResult
                        assertion="l7p:RemoteIpAddressRange" status="Assertion Falsified">
                        <l7:detailMessage id="4503">Requestor address 52.214.1.251 is not allowed</l7:detailMessage>
                    </l7:assertionResult>
                    <l7:assertionResult
                        assertion="l7p:RemoteIpAddressRange" status="Assertion Falsified">
                        <l7:detailMessage id="4503">Requestor address 52.214.1.251 is not allowed</l7:detailMessage>
                    </l7:assertionResult>
                    <l7:assertionResult
                        assertion="l7p:RemoteIpAddressRange" status="Assertion Falsified">
                        <l7:detailMessage id="4503">Requestor address 52.214.1.251 is not allowed</l7:detailMessage>
                    </l7:assertionResult>
                    <l7:assertionResult
                        assertion="l7p:RemoteIpAddressRange" status="Assertion Falsified">
                        <l7:detailMessage id="4503">Requestor address 52.214.1.251 is not allowed</l7:detailMessage>
                    </l7:assertionResult>
                    <l7:assertionResult
                        assertion="l7p:RemoteIpAddressRange" status="Assertion Falsified">
                        <l7:detailMessage id="4503">Requestor address 52.214.1.251 is not allowed</l7:detailMessage>
                    </l7:assertionResult>
                    <l7:assertionResult
                        assertion="l7p:RemoteIpAddressRange" status="Assertion Falsified">
                        <l7:detailMessage id="4503">Requestor address 52.214.1.251 is not allowed</l7:detailMessage>
                    </l7:assertionResult>
                    <l7:assertionResult
                        assertion="l7p:RemoteIpAddressRange" status="Assertion Falsified">
                        <l7:detailMessage id="4503">Requestor address 52.214.1.251 is not allowed</l7:detailMessage>
                    </l7:assertionResult>
                    <l7:assertionResult
                        assertion="l7p:RemoteIpAddressRange" status="Assertion Falsified">
                        <l7:detailMessage id="4503">Requestor address 52.214.1.251 is not allowed</l7:detailMessage>
                    </l7:assertionResult>
                    <l7:assertionResult
                        assertion="l7p:RemoteIpAddressRange" status="Assertion Falsified">
                        <l7:detailMessage id="4503">Requestor address 52.214.1.251 is not allowed</l7:detailMessage>
                    </l7:assertionResult>
                    <l7:assertionResult
                        assertion="l7p:RemoteIpAddressRange" status="Assertion Falsified">
                        <l7:detailMessage id="4503">Requestor address 52.214.1.251 is not allowed</l7:detailMessage>
                    </l7:assertionResult>
                    <l7:assertionResult
                        assertion="l7p:RemoteIpAddressRange" status="Assertion Falsified">
                        <l7:detailMessage id="4503">Requestor address 52.214.1.251 is not allowed</l7:detailMessage>
                    </l7:assertionResult>
                    <l7:assertionResult
                        assertion="l7p:RemoteIpAddressRange" status="Assertion Falsified">
                        <l7:detailMessage id="4503">Requestor address 52.214.1.251 is not allowed</l7:detailMessage>
                    </l7:assertionResult>
                    <l7:assertionResult
                        assertion="l7p:RemoteIpAddressRange" status="Assertion Falsified">
                        <l7:detailMessage id="4503">Requestor address 52.214.1.251 is not allowed</l7:detailMessage>
                    </l7:assertionResult>
                    <l7:assertionResult
                        assertion="l7p:RemoteIpAddressRange" status="Assertion Falsified">
                        <l7:detailMessage id="4503">Requestor address 52.214.1.251 is not allowed</l7:detailMessage>
                    </l7:assertionResult>
                    <l7:assertionResult
                        assertion="l7p:RemoteIpAddressRange" status="Assertion Falsified">
                        <l7:detailMessage id="4503">Requestor address 52.214.1.251 is not allowed</l7:detailMessage>
                    </l7:assertionResult>
                    <l7:assertionResult
                        assertion="l7p:RemoteIpAddressRange" status="Assertion Falsified">
                        <l7:detailMessage id="4503">Requestor address 52.214.1.251 is not allowed</l7:detailMessage>
                    </l7:assertionResult>
                    <l7:assertionResult
                        assertion="l7p:RemoteIpAddressRange" status="Assertion Falsified">
                        <l7:detailMessage id="4503">Requestor address 52.214.1.251 is not allowed</l7:detailMessage>
                    </l7:assertionResult>
                    <l7:assertionResult
                        assertion="l7p:RemoteIpAddressRange" status="Assertion Falsified">
                        <l7:detailMessage id="4503">Requestor address 52.214.1.251 is not allowed</l7:detailMessage>
                    </l7:assertionResult>
                    <l7:assertionResult
                        assertion="l7p:RemoteIpAddressRange" status="Assertion Falsified">
                        <l7:detailMessage id="4503">Requestor address 52.214.1.251 is not allowed</l7:detailMessage>
                    </l7:assertionResult>
                    <l7:assertionResult
                        assertion="l7p:RemoteIpAddressRange" status="Assertion Falsified">
                        <l7:detailMessage id="4503">Requestor address 52.214.1.251 is not allowed</l7:detailMessage>
                    </l7:assertionResult>
                    <l7:assertionResult
                        assertion="l7p:RemoteIpAddressRange" status="Assertion Falsified">
                        <l7:detailMessage id="4503">Requestor address 52.214.1.251 is not allowed</l7:detailMessage>
                    </l7:assertionResult>
                    <l7:assertionResult
                        assertion="l7p:RemoteIpAddressRange" status="Assertion Falsified">
                        <l7:detailMessage id="4503">Requestor address 52.214.1.251 is not allowed</l7:detailMessage>
                    </l7:assertionResult>
                    <l7:assertionResult
                        assertion="l7p:RemoteIpAddressRange" status="Assertion Falsified">
                        <l7:detailMessage id="4503">Requestor address 52.214.1.251 is not allowed</l7:detailMessage>
                    </l7:assertionResult>
                    <l7:assertionResult
                        assertion="l7p:RemoteIpAddressRange" status="Assertion Falsified">
                        <l7:detailMessage id="4503">Requestor address 52.214.1.251 is not allowed</l7:detailMessage>
                    </l7:assertionResult>
                    <l7:assertionResult
                        assertion="l7p:RemoteIpAddressRange" status="Assertion Falsified">
                        <l7:detailMessage id="4503">Requestor address 52.214.1.251 is not allowed</l7:detailMessage>
                    </l7:assertionResult>
                    <l7:assertionResult
                        assertion="l7p:RemoteIpAddressRange" status="Assertion Falsified">
                        <l7:detailMessage id="4503">Requestor address 52.214.1.251 is not allowed</l7:detailMessage>
                    </l7:assertionResult>
                    <l7:assertionResult
                        assertion="l7p:RemoteIpAddressRange" status="Assertion Falsified">
                        <l7:detailMessage id="4503">Requestor address 52.214.1.251 is not allowed</l7:detailMessage>
                    </l7:assertionResult>
                    <l7:assertionResult
                        assertion="l7p:RemoteIpAddressRange" status="Assertion Falsified">
                        <l7:detailMessage id="4503">Requestor address 52.214.1.251 is not allowed</l7:detailMessage>
                    </l7:assertionResult>
                    <l7:assertionResult
                        assertion="l7p:RemoteIpAddressRange" status="Assertion Falsified">
                        <l7:detailMessage id="4503">Requestor address 52.214.1.251 is not allowed</l7:detailMessage>
                    </l7:assertionResult>
                    <l7:assertionResult
                        assertion="l7p:RemoteIpAddressRange" status="Assertion Falsified">
                        <l7:detailMessage id="4503">Requestor address 52.214.1.251 is not allowed</l7:detailMessage>
                    </l7:assertionResult>
                    <l7:assertionResult
                        assertion="l7p:RemoteIpAddressRange" status="Assertion Falsified">
                        <l7:detailMessage id="4503">Requestor address 52.214.1.251 is not allowed</l7:detailMessage>
                    </l7:assertionResult>
                    <l7:assertionResult assertion="l7p:OneOrMore" status="Assertion Falsified"/>
                    <l7:assertionResult assertion="l7p:All" status="Assertion Falsified"/>
                </l7:policyResult>
            </detail>
        </soapenv:Fault>
    </soapenv:Body>
</soapenv:Envelope>
